lextoplus/LexToPlus.py
lextoplus/__init__.py
lextoplus/resource/bigthai.txt
lextoplus/resource/full.lex.config
lextoplus-0.0.5.dist-info/METADATA
lextoplus-0.0.5.dist-info/WHEEL
lextoplus-0.0.5.dist-info/top_level.txt
lextoplus-0.0.5.dist-info/RECORD
